cpcontest/__init__.py
cpcontest/__main__.py
cpcontest/cli.py
cpcontest/config.py
cpcontest/constants.py
cpcontest/platforms/__init__.py
cpcontest/platforms/base.py
cpcontest/platforms/codechef.py
cpcontest/platforms/codeforces.py
cpcontest/platforms/generic.py
cpcontest/platforms/rpc.py
cpcontest/platforms/vjudge.py
cpcontest/utils/__init__.py
cpcontest/utils/editor.py
cpcontest/utils/filesystem.py
cpcontest/utils/template.py
cpcontest_setup-1.0.0.dist-info/licenses/LICENSE
tests/__init__.py
tests/test_platforms.py
tests/test_utils.py
cpcontest_setup-1.0.0.dist-info/METADATA
cpcontest_setup-1.0.0.dist-info/WHEEL
cpcontest_setup-1.0.0.dist-info/entry_points.txt
cpcontest_setup-1.0.0.dist-info/top_level.txt
cpcontest_setup-1.0.0.dist-info/RECORD
