Metadata-Version: 2.4
Name: cpcontest-setup
Version: 1.0.0
Summary: Generador automático de estructuras para concursos de programación competitiva modo Colombiano
Home-page: https://github.com/josuerom/cpcontest-setup
Author: josuerom
Author-email: josuerom <josueromram3@gmail.com>
License: MIT
Project-URL: Homepage, https://github.com/josuerom/cpcontest-setup
Project-URL: Bug Tracker, https://github.com/josuerom/cpcontest-setup/issues
Keywords: CP,competitive programming,codeforces,RPC,HackerRank,VJudge,CodeChef,contests,automation
Classifier: Development Status :: 4 - Beta
Classifier: Intended Audience :: Developers
Classifier: Topic :: Software Development :: Code Generators
Classifier: License :: OSI Approved :: MIT License
Classifier: Programming Language :: Python :: 3
Classifier: Operating System :: OS Independent
Requires-Python: >=3.10
License-File: LICENSE
Dynamic: author
Dynamic: home-page
Dynamic: license-file
Dynamic: requires-python
